mlab_amo_async/__init__.py
mlab_amo_async/account.py
mlab_amo_async/amocrm_client.py
mlab_amo_async/async_interaction.py
mlab_amo_async/cli.py
mlab_amo_async/exceptions.py
mlab_amo_async/fields.py
mlab_amo_async/filters.py
mlab_amo_async/interaction.py
mlab_amo_async/links.py
mlab_amo_async/manager.py
mlab_amo_async/model.py
mlab_amo_async/register.py
mlab_amo_async/tokens.py
mlab_amo_async/entity/__init__.py
mlab_amo_async/entity/call.py
mlab_amo_async/entity/company.py
mlab_amo_async/entity/contact.py
mlab_amo_async/entity/custom_field.py
mlab_amo_async/entity/customer.py
mlab_amo_async/entity/events.py
mlab_amo_async/entity/lead.py
mlab_amo_async/entity/list.py
mlab_amo_async/entity/note.py
mlab_amo_async/entity/pipeline.py
mlab_amo_async/entity/tag.py
mlab_amo_async/entity/task.py
mlab_amo_async/entity/user.py
mlab_amo_async-0.0.5.dist-info/METADATA
mlab_amo_async-0.0.5.dist-info/WHEEL
mlab_amo_async-0.0.5.dist-info/top_level.txt
mlab_amo_async-0.0.5.dist-info/RECORD
