Metadata-Version: 2.2
Name: mlab_amo_async
Version: 0.0.5
Summary: Небольшая библиотека для работы с AmoCRM+MongoDB
Author: MLAB
Requires-Dist: requests
Requires-Dist: pyjwt
Requires-Dist: motor
Requires-Dist: importlib-metadata; python_version < "3.11"
Dynamic: author
Dynamic: requires-dist
Dynamic: summary
